perun/__init__.py
perun/__main__.py
perun/comm.py
perun/configuration.py
perun/coordination.py
perun/core.py
perun/logging.py
perun/processing.py
perun/py.typed
perun/util.py
perun/version.py
perun/api/__init__.py
perun/api/cli.py
perun/api/decorator.py
perun/backend/__init__.py
perun/backend/backend.py
perun/backend/nvml.py
perun/backend/powercap_rapl.py
perun/backend/psutil.py
perun/backend/rocmsmi.py
perun/backend/util.py
perun/data_model/__init__.py
perun/data_model/data.py
perun/data_model/measurement_type.py
perun/data_model/sensor.py
perun/io/__init__.py
perun/io/bench.py
perun/io/hdf5.py
perun/io/io.py
perun/io/json.py
perun/io/pandas.py
perun/io/pickle.py
perun/io/text_report.py
perun/io/util.py
perun/monitoring/__init__.py
perun/monitoring/application.py
perun/monitoring/monitor.py
perun/monitoring/subprocess.py
perun-0.9.0.dist-info/METADATA
perun-0.9.0.dist-info/WHEEL
perun-0.9.0.dist-info/entry_points.txt
perun-0.9.0.dist-info/licenses/LICENSE
perun-0.9.0.dist-info/RECORD
