Metadata-Version: 2.4
Name: perun
Version: 0.9.0
Summary: Measure the energy used by your MPI+Python applications.
Project-URL: Homepage, https://github.com/Helmholtz-AI-Energy/perun
Project-URL: Documentation, https://perun.readthedocs.io
Project-URL: Repository, https://github.com/Helmholtz-AI-Energy/perun
Project-URL: Issues, https://github.com/Helmholtz-AI-Energy/perun/issues
Project-URL: Changelog, https://github.com/Helmholtz-AI-Energy/perun/blob/main/CHANGELOG.md
Author-email: "Gutiérrez Hermosillo Muriedas, Juan Pedro" <juan.muriedas@kit.edu>
Maintainer-email: "Gutiérrez Hermosillo Muriedas, Juan Pedro" <juan.muriedas@kit.edu>
License: BSD 3-Clause License
License-File: LICENSE
Keywords: benchmarking,command-line,energy,hpc,monitoring,mpi,python
Classifier: Development Status :: 4 - Beta
Classifier: Environment :: Console
Classifier: Intended Audience :: Developers
Classifier: Intended Audience :: Science/Research
Classifier: License :: OSI Approved :: BSD License
Classifier: Programming Language :: Python :: 3
Classifier: Topic :: Scientific/Engineering
Classifier: Topic :: System :: Benchmark
Classifier: Topic :: System :: Distributed Computing
Classifier: Topic :: System :: Hardware
Classifier: Topic :: System :: Monitoring
Classifier: Typing :: Typed
Requires-Python: >=3.9
Requires-Dist: h5py>=3.5.9
Requires-Dist: numpy>=1.20.0
Requires-Dist: pandas>=1.3
Requires-Dist: psutil>=5.9.0
Requires-Dist: py-cpuinfo>=5.0.0
Requires-Dist: tabulate>=0.9
Provides-Extra: dev
Requires-Dist: build; extra == 'dev'
Requires-Dist: coverage; extra == 'dev'
Requires-Dist: hypothesis~=6.100; extra == 'dev'
Requires-Dist: pre-commit; extra == 'dev'
Requires-Dist: pytest; extra == 'dev'
Requires-Dist: python-semantic-release>=8.1.1; extra == 'dev'
Provides-Extra: docs
Requires-Dist: furo; extra == 'docs'
Requires-Dist: sphinx; extra == 'docs'
Requires-Dist: sphinx-autoapi; extra == 'docs'
Requires-Dist: sphinx-autobuild; extra == 'docs'
Provides-Extra: mpi
Requires-Dist: mpi4py>=3.1; extra == 'mpi'
Provides-Extra: nvidia
Requires-Dist: nvidia-ml-py>=12.535.77; extra == 'nvidia'
Provides-Extra: rocm
Requires-Dist: amdsmi>=6.2.0; extra == 'rocm'
